kolada_mcp/__init__.py
kolada_mcp/config.py
kolada_mcp/kpi_embeddings.npz
kolada_mcp/server.py
kolada_mcp/lifespan/__init__.py
kolada_mcp/lifespan/context.py
kolada_mcp/models/__init__.py
kolada_mcp/models/types.py
kolada_mcp/prompts/__init__.py
kolada_mcp/prompts/entry_prompt.py
kolada_mcp/services/__init__.py
kolada_mcp/services/api.py
kolada_mcp/services/data_processing.py
kolada_mcp/services/embeddings.py
kolada_mcp/tools/__init__.py
kolada_mcp/tools/comparison_tools.py
kolada_mcp/tools/data_tools.py
kolada_mcp/tools/metadata_tools.py
kolada_mcp/tools/municipality_tools.py
kolada_mcp/tools/url_builders.py
kolada_mcp/utils/__init__.py
kolada_mcp/utils/context.py
kolada_mcp/utils/statistics.py
kolada_mcp-0.1.36.dist-info/licenses/LICENSE
kolada_mcp-0.1.36.dist-info/METADATA
kolada_mcp-0.1.36.dist-info/WHEEL
kolada_mcp-0.1.36.dist-info/entry_points.txt
kolada_mcp-0.1.36.dist-info/top_level.txt
kolada_mcp-0.1.36.dist-info/RECORD
