Metadata-Version: 2.4
Name: kolada-mcp
Version: 0.1.36
Summary: MCP server for Kolada API
Author-email: Hugi Aegisberg <hugi.aegisberg@pm.me>
License-Expression: Apache-2.0
Project-URL: Homepage, https://github.com/aerugo/kolada-mcp
Project-URL: Bug Tracker, https://github.com/aerugo/kolada-mcp/issues
Requires-Python: >=3.12
License-File: LICENSE
Requires-Dist: httpx>=0.28.1
Requires-Dist: mcp[cli]>=1.6.0
Requires-Dist: numpy>=2.2.4
Requires-Dist: polars>=1.26.0
Requires-Dist: sentence-transformers>=4.0.1
Requires-Dist: statistics>=1.0.3.5
Dynamic: license-file
